bike/__init__.py
bike/bike.py
env/__init__.py
env/env.py
evolution/__init__.py
evolution/evo.py
visualiation/__init__.py
visualiation/vis.py
genetic_bike_ictp_2024-0.1.0.dist-info/METADATA
genetic_bike_ictp_2024-0.1.0.dist-info/WHEEL
genetic_bike_ictp_2024-0.1.0.dist-info/entry_points.txt
genetic_bike_ictp_2024-0.1.0.dist-info/top_level.txt
genetic_bike_ictp_2024-0.1.0.dist-info/RECORD
